{
  "font-size-xs": {
    "$type": "number",
    "$value": 10
  },
  "font-size-sm": {
    "$type": "number",
    "$value": 11
  },
  "font-size-base": {
    "$type": "number",
    "$value": 13
  },
  "font-size-md": {
    "$type": "number",
    "$value": 14
  },
  "font-size-lg": {
    "$type": "number",
    "$value": 16
  },
  "font-size-xl": {
    "$type": "number",
    "$value": 20
  },
  "font-size-2xl": {
    "$type": "number",
    "$value": 24
  },
  "font-family-sans": {
    "$type": "fontFamily",
    "$value": "Inter"
  },
  "font-family-mono": {
    "$type": "fontFamily",
    "$value": "JetBrains Mono"
  }
}
